aio_prometheus_client/__init__.py
aio_prometheus_client/client.py
aio_prometheus_client/errors.py
aio_prometheus_client/model.py
aio_prometheus_client/py.typed
aio_prometheus_client-0.1.1.dist-info/METADATA
aio_prometheus_client-0.1.1.dist-info/WHEEL
aio_prometheus_client-0.1.1.dist-info/top_level.txt
aio_prometheus_client-0.1.1.dist-info/RECORD
