Metadata-Version: 2.1
Name: aio-prometheus-client
Version: 0.1.1
Summary: Prometheus Http Client for Asyncio
Home-page: https://github.com/lexdene/python-aio-prometheus-client
License: LGPL
Requires-Python: >3.10.0
Requires-Dist: httpx
